odoo9_addon_printer_tray-9.0.1.0.1-py2.7-nspkg.pth
odoo_addons/printer_tray/__openerp__.py
odoo_addons/printer_tray/__init__.py
odoo_addons/printer_tray/README.rst
odoo_addons/printer_tray/security/ir.model.access.csv
odoo_addons/printer_tray/models/printing_printer.py
odoo_addons/printer_tray/models/printing_report_xml_action.py
odoo_addons/printer_tray/models/printing_tray.py
odoo_addons/printer_tray/models/__init__.py
odoo_addons/printer_tray/models/ir_actions_report_xml.py
odoo_addons/printer_tray/models/res_users.py
odoo_addons/printer_tray/i18n/zh_CN.po
odoo_addons/printer_tray/i18n/printer_tray.po
odoo_addons/printer_tray/i18n/pt.po
odoo_addons/printer_tray/i18n/it.po
odoo_addons/printer_tray/i18n/es.po
odoo_addons/printer_tray/i18n/tr.po
odoo_addons/printer_tray/i18n/hr.po
odoo_addons/printer_tray/i18n/bg.po
odoo_addons/printer_tray/i18n/gl.po
odoo_addons/printer_tray/i18n/ca.po
odoo_addons/printer_tray/i18n/sl.po
odoo_addons/printer_tray/i18n/es_ES.po
odoo_addons/printer_tray/i18n/pt_PT.po
odoo_addons/printer_tray/i18n/nl.po
odoo_addons/printer_tray/i18n/am.po
odoo_addons/printer_tray/i18n/de.po
odoo_addons/printer_tray/i18n/fr.po
odoo_addons/printer_tray/i18n/pt_BR.po
odoo_addons/printer_tray/i18n/el_GR.po
odoo_addons/printer_tray/i18n/fi.po
odoo_addons/printer_tray/i18n/hr_HR.po
odoo_addons/printer_tray/views/ir_actions_report_xml.xml
odoo_addons/printer_tray/views/printing_report_xml_action.xml
odoo_addons/printer_tray/views/res_users.xml
odoo_addons/printer_tray/views/printing_printer.xml
odoo_addons/printer_tray/tests/test_printing_printer.py
odoo_addons/printer_tray/tests/test_printing_tray.py
odoo_addons/printer_tray/tests/__init__.py
odoo9_addon_printer_tray-9.0.1.0.1.dist-info/top_level.txt
odoo9_addon_printer_tray-9.0.1.0.1.dist-info/WHEEL
odoo9_addon_printer_tray-9.0.1.0.1.dist-info/RECORD
odoo9_addon_printer_tray-9.0.1.0.1.dist-info/metadata.json
odoo9_addon_printer_tray-9.0.1.0.1.dist-info/DESCRIPTION.rst
odoo9_addon_printer_tray-9.0.1.0.1.dist-info/METADATA
odoo9_addon_printer_tray-9.0.1.0.1.dist-info/namespace_packages.txt
